setup.py
isingmodel/Ising.py
isingmodel/Lattice.py
isingmodel/__init__.py
isingmodel.egg-info/PKG-INFO
isingmodel.egg-info/SOURCES.txt
isingmodel.egg-info/dependency_links.txt
isingmodel.egg-info/not-zip-safe
isingmodel.egg-info/top_level.txt