Metadata-Version: 1.0
Name: isingmodel
Version: 0.1
Summary: 2D Ising model simulation
Home-page: https://github.com/rbnvrw/2DIsingModel
Author: Ruben Verweij
Author-email: development@rubenverweij.nl
License: MIT
Platform: UNKNOWN
